sentrylogs/__init__.py
sentrylogs/daemonize.py
sentrylogs/helpers.py
sentrylogs/bin/__init__.py
sentrylogs/bin/sentrylogs.py
sentrylogs/conf/__init__.py
sentrylogs/conf/settings.py
sentrylogs/parsers/__init__.py
sentrylogs/parsers/nginx.py
SentryLogs-0.5.0.dist-info/AUTHORS.txt
SentryLogs-0.5.0.dist-info/LICENSE.txt
SentryLogs-0.5.0.dist-info/METADATA
SentryLogs-0.5.0.dist-info/WHEEL
SentryLogs-0.5.0.dist-info/entry_points.txt
SentryLogs-0.5.0.dist-info/top_level.txt
SentryLogs-0.5.0.dist-info/RECORD
