Metadata-Version: 2.1
Name: SentryLogs
Version: 0.5.0
Summary: Send logs from Nginx and other applications to Sentry.
Home-page: https://github.com/mdgart/sentrylogs
Author: Mauro De Giorgi
Author-email: mauro.degiorgi@gmail.com
License: BSD
Platform: UNKNOWN
Classifier: Intended Audience :: Developers
Classifier: License :: OSI Approved :: BSD License
Classifier: Operating System :: OS Independent
Classifier: Programming Language :: Python
Classifier: Programming Language :: Python :: 2
Classifier: Programming Language :: Python :: 2.7
Classifier: Programming Language :: Python :: 3
Classifier: Programming Language :: Python :: 3.4
Classifier: Programming Language :: Python :: 3.5
Classifier: Programming Language :: Python :: 3.6
Classifier: Programming Language :: Python :: 3.7
Requires-Dist: sentry-sdk (<1.0.0,>=0.7.9)
Requires-Dist: tailhead (>=1.0.2)
